openscenesense_ollama/__init__.py
openscenesense_ollama/analyzer.py
openscenesense_ollama/cli.py
openscenesense_ollama/exceptions.py
openscenesense_ollama/frame_selectors.py
openscenesense_ollama/models.py
openscenesense_ollama/transcriber.py
openscenesense_ollama/video_utils.py
openscenesense_ollama-1.1.0.dist-info/METADATA
openscenesense_ollama-1.1.0.dist-info/WHEEL
openscenesense_ollama-1.1.0.dist-info/entry_points.txt
openscenesense_ollama-1.1.0.dist-info/licenses/LICENSE
openscenesense_ollama-1.1.0.dist-info/RECORD
