Metadata-Version: 2.4
Name: openscenesense-ollama
Version: 1.1.0
Summary: Offline video analysis using Ollama models and local Whisper
Project-URL: Homepage, https://github.com/ymrohit/openscenesense-ollama
Project-URL: Repository, https://github.com/ymrohit/openscenesense-ollama.git
Author-email: Rohit Yelukati Mahendra <mahendrarohittigon@gmail.com>
License-File: LICENSE
Classifier: License :: OSI Approved :: MIT License
Classifier: Operating System :: OS Independent
Classifier: Programming Language :: Python :: 3
Requires-Python: >=3.10
Requires-Dist: ffmpeg-python>=0.2.0
Requires-Dist: librosa>=0.10.2.post1
Requires-Dist: numpy>=2.0.2
Requires-Dist: opencv-python>=4.10.0.84
Requires-Dist: pillow>=11.0.0
Requires-Dist: requests>=2.32.3
Requires-Dist: torch>=2.5.1
Requires-Dist: transformers>=4.46.1
Provides-Extra: dev
Requires-Dist: pytest; extra == 'dev'
